pybliometrics/__init__.py
pybliometrics/exception.py
pybliometrics/sciencedirect/__init__.py
pybliometrics/sciencedirect/article_entitlement.py
pybliometrics/sciencedirect/article_metadata.py
pybliometrics/sciencedirect/article_retrieval.py
pybliometrics/sciencedirect/nonserial_title.py
pybliometrics/sciencedirect/object_metadata.py
pybliometrics/sciencedirect/object_retrieval.py
pybliometrics/sciencedirect/sciencedirect_search.py
pybliometrics/sciencedirect/subject_classifications.py
pybliometrics/sciencedirect/tests/__init__.py
pybliometrics/sciencedirect/tests/test_ArticleEntitlement.py
pybliometrics/sciencedirect/tests/test_ArticleMetadata.py
pybliometrics/sciencedirect/tests/test_ArticleRetrieval.py
pybliometrics/sciencedirect/tests/test_NonserialTitle.py
pybliometrics/sciencedirect/tests/test_ObjectMetadata.py
pybliometrics/sciencedirect/tests/test_ObjectRetrieval.py
pybliometrics/sciencedirect/tests/test_ScienceDirectSearch.py
pybliometrics/sciencedirect/tests/test_SerialTitleISSN.py
pybliometrics/sciencedirect/tests/test_SubjectClassifications.py
pybliometrics/scival/__init__.py
pybliometrics/scival/author_metrics.py
pybliometrics/scival/institution_lookup_metrics.py
pybliometrics/scival/publication_lookup.py
pybliometrics/scival/topic_lookup_metrics.py
pybliometrics/scival/tests/test_AuthorMetrics.py
pybliometrics/scival/tests/test_InstitutionLookupMetrics.py
pybliometrics/scival/tests/test_PublicationLookup.py
pybliometrics/scival/tests/test_TopicLookupMetrics.py
pybliometrics/scopus/__init__.py
pybliometrics/scopus/abstract_citation.py
pybliometrics/scopus/abstract_retrieval.py
pybliometrics/scopus/affiliation_retrieval.py
pybliometrics/scopus/affiliation_search.py
pybliometrics/scopus/author_retrieval.py
pybliometrics/scopus/author_search.py
pybliometrics/scopus/plumx_metrics.py
pybliometrics/scopus/scopus_search.py
pybliometrics/scopus/serial_title_issn.py
pybliometrics/scopus/serial_title_search.py
pybliometrics/scopus/subject_classifications.py
pybliometrics-4.4.1.dist-info/licenses/LICENSE
pybliometrics-4.4.1.dist-info/METADATA
pybliometrics-4.4.1.dist-info/WHEEL
pybliometrics-4.4.1.dist-info/top_level.txt
pybliometrics-4.4.1.dist-info/RECORD
