Metadata-Version: 2.4
Name: pybliometrics
Version: 4.4.1
Summary: Python-based API-Wrapper to access Scopus and ScienceDirect
Author-email: "'John Kitchin and Michael E. Rose" <Michael.Ernst.Rose@gmail.com>
Maintainer-email: "Michael E. Rose" <Michael.Ernst.Rose@gmail.com>
License-Expression: MIT
Project-URL: Homepage, https://github.com/pybliometrics-dev/pybliometrics
Project-URL: Bug Tracker, https://github.com/pybliometrics-dev/pybliometrics/issues
Project-URL: Documentation (stable), https://pybliometrics.readthedocs.io/en/stable/
Project-URL: Documentation (latest), https://pybliometrics.readthedocs.io/en/latest/
Keywords: scopus
Classifier: Development Status :: 5 - Production/Stable
Classifier: Intended Audience :: Science/Research
Classifier: Intended Audience :: Developers
Classifier: Natural Language :: English
Classifier: Operating System :: OS Independent
Classifier: Programming Language :: Python :: 3.10
Classifier: Programming Language :: Python :: 3.11
Classifier: Programming Language :: Python :: 3.12
Classifier: Programming Language :: Python :: 3.13
Classifier: Topic :: Software Development :: Libraries :: Python Modules
Classifier: Topic :: Scientific/Engineering :: Information Analysis
Classifier: Topic :: Documentation :: Sphinx
Requires-Python: >=3.10
License-File: LICENSE
Requires-Dist: requests
Requires-Dist: tqdm
Requires-Dist: urllib3
Provides-Extra: test
Requires-Dist: pytest; extra == "test"
Requires-Dist: Pillow; extra == "test"
Dynamic: license-file
